flask_api_tools/__init__.py
flask_api_tools/rate_limiting/__init__.py
flask_api_tools/rate_limiting/in_memory_limiter.py
flask_api_tools/rate_limiting/redis_limiter.py
flask_api_tools/validators/__init__.py
flask_api_tools/validators/data_set.py
flask_api_tools/validators/sanitised_data_set.py
flask_api_tools/validators/validator.py
tests/__init__.py
tests/conftest.py
tests/rate_limiting/__init__.py
tests/rate_limiting/test_in_memory_limiter.py
tests/validators/__init__.py
tests/validators/example_data_sets.py
tests/validators/test_data_set.py
tests/validators/test_sanitised_data_set.py
tests/validators/test_validator.py
flask_api_tools-1.6.3.dist-info/LICENSE
flask_api_tools-1.6.3.dist-info/METADATA
flask_api_tools-1.6.3.dist-info/WHEEL
flask_api_tools-1.6.3.dist-info/top_level.txt
flask_api_tools-1.6.3.dist-info/RECORD
