Metadata-Version: 2.1
Name: flask-api-tools
Version: 1.6.3
Summary: Tooling to assist with building Flask APIs
Home-page: https://github.com/ScholarPack/flask-api-tools
Author: ScholarPack
Author-email: dev@scholarpack.com
License: UNKNOWN
Platform: UNKNOWN
Classifier: Development Status :: 5 - Production/Stable
Classifier: Programming Language :: Python :: 3
Classifier: License :: OSI Approved :: MIT License
Classifier: Operating System :: OS Independent
Requires-Python: >=3.8
Requires-Dist: flask (>=1.1)
Requires-Dist: flask-limiter (>=1.3)
Requires-Dist: redis (>=2.10)
Requires-Dist: bleach (>=3.1)
Requires-Dist: cerberus (>=1.3)
